mm_okx/__init__.py
mm_okx/logger.py
mm_okx/py.typed
mm_okx/utils.py
mm_okx/api/__init__.py
mm_okx/api/account.py
mm_okx/api/public.py
mm_okx/cli/__init__.py
mm_okx/cli/main.py
mm_okx/cli/utils.py
mm_okx/cli/commands/__init__.py
mm_okx/cli/commands/account_commands.py
mm_okx/cli/commands/public_commands.py
mm_okx/cli/commands/account/__init__.py
mm_okx/cli/commands/account/balances.py
mm_okx/cli/commands/account/buy_market.py
mm_okx/cli/commands/account/currencies.py
mm_okx/cli/commands/account/deposit_address.py
mm_okx/cli/commands/account/deposit_history.py
mm_okx/cli/commands/account/funding_balances.py
mm_okx/cli/commands/account/order_history.py
mm_okx/cli/commands/account/sell_market.py
mm_okx/cli/commands/account/trading_balances.py
mm_okx/cli/commands/account/transfer_to_funding.py
mm_okx/cli/commands/account/transfer_to_trading.py
mm_okx/cli/commands/account/withdraw.py
mm_okx/cli/commands/account/withdrawal_history.py
mm_okx/cli/commands/public/__init__.py
mm_okx/cli/commands/public/instrument.py
mm_okx/cli/commands/public/instruments.py
mm_okx/cli/commands/public/ticker.py
mm_okx/cli/commands/public/tickers.py
mm_okx-0.3.5.dist-info/METADATA
mm_okx-0.3.5.dist-info/WHEEL
mm_okx-0.3.5.dist-info/entry_points.txt
mm_okx-0.3.5.dist-info/RECORD
