Metadata-Version: 2.4
Name: mm-okx
Version: 0.3.5
Requires-Python: >=3.14
Requires-Dist: mm-http~=0.2.5
Requires-Dist: mm-print~=0.2.3
Requires-Dist: typer~=0.21.1
